class_cache/__init__.py
class_cache/backends.py
class_cache/core.py
class_cache/lru_queue.py
class_cache/types.py
class_cache/utils.py
class_cache/wrappers.py
class_cache-0.10.1.dist-info/LICENSE
class_cache-0.10.1.dist-info/WHEEL
class_cache-0.10.1.dist-info/METADATA
class_cache-0.10.1.dist-info/RECORD
