Metadata-Version: 2.1
Name: class-cache
Version: 0.10.1
Summary: Caching for class based generators
Maintainer-email: Artem Vasenin <vasart169@gmail.com>
Requires-Python: >=3.10
Requires-Dist: Pympler
Requires-Dist: brotli
Requires-Dist: marisa-trie
Requires-Dist: replete>=2.3.1
Requires-Dist: black ; extra == "dev"
Requires-Dist: class-cache[test] ; extra == "dev"
Requires-Dist: isort ; extra == "dev"
Requires-Dist: numpy ; extra == "dev"
Requires-Dist: pre-commit ; extra == "dev"
Requires-Dist: ruff ; extra == "dev"
Requires-Dist: flaky ; extra == "test"
Requires-Dist: pytest ; extra == "test"
Requires-Dist: pytest-cov ; extra == "test"
Requires-Dist: replete[testing] ; extra == "test"
Project-URL: Home, https://github.com/Rizhiy/class-cache
Provides-Extra: dev
Provides-Extra: test
